conftest.py
notebook_shim/__init__.py
notebook_shim/_version.py
notebook_shim/nbserver.py
notebook_shim/shim.py
notebook_shim/traits.py
elixir_shim-0.2.2.data/data/etc/jupyter/jupyter_server_config.d/notebook_shim.json
elixir_shim-0.2.2.dist-info/METADATA
elixir_shim-0.2.2.dist-info/WHEEL
elixir_shim-0.2.2.dist-info/licenses/LICENSE
elixir_shim-0.2.2.dist-info/RECORD
