Metadata-Version: 2.1
Name: elixir_shim
Version: 0.2.2
Summary: A shim layer for notebook traits and config
Author-email: ciusji <bqjimaster@gmail.com>
License: BSD 3-Clause License
License-File: LICENSE
Keywords: ipython,jupyter
Classifier: Framework :: Jupyter
Classifier: Intended Audience :: Developers
Classifier: Intended Audience :: Science/Research
Classifier: Intended Audience :: System Administrators
Classifier: License :: OSI Approved :: BSD License
Classifier: Programming Language :: Python
Classifier: Programming Language :: Python :: 3
Classifier: Programming Language :: Python :: 3 :: Only
Classifier: Programming Language :: Python :: 3.7
Classifier: Programming Language :: Python :: 3.8
Classifier: Programming Language :: Python :: 3.9
Classifier: Programming Language :: Python :: 3.10
Requires-Python: >=3.7
Requires-Dist: elixir-server>=2.1.0.dev204
Provides-Extra: test
Requires-Dist: pytest; extra == 'test'
Requires-Dist: pytest-console-scripts; extra == 'test'
Requires-Dist: pytest-tornasync; extra == 'test'
